<?xml version="1.0" encoding="utf-8"?>
<repositorys>
	<repository>
		<name>SysUserQuery</name>
		<action>com.yun9.sys.inst.support.service.SysUserQueryService</action>
		<output>      
			<classname>com.yun9.mobile.framework.model.User</classname>
			<type>list</type>
		</output>
		<type>yun9</type>
	</repository>
	<repository>
		<name>SysUserPasswdValidate</name>
		<action>com.yun9.sys.inst.support.service.SysUserPasswdValidateService</action>
		<output>
			<classname>com.yun9.mobile.framework.model.AuthInfo</classname>
			<type>object</type>
		</output>
		<type>yun9</type>
	</repository>
	
	<!--根据机构id查询所有用户信息  -->
	<repository>
	    <name>SysUserQueryByInstService</name>
	    <action>com.yun9.sys.inst.support.service.SysUserQueryByInstService</action>
		<output>
			<classname>com.yun9.mobile.framework.model.User</classname>
			<type>list</type>
		</output>
		<type>yun9</type>
	</repository>
	
	<!--根据組織id查询所有用户信息  -->
	<repository>
	    <name>SysUserByOrgService</name>
	    <action>com.yun9.sys.inst.support.service.SysUserByOrgService</action>
		<output>
			<classname>com.yun9.mobile.framework.model.User</classname>
			<type>list</type>
		</output>
		<type>yun9</type>
	</repository>
	
	<!--根据机构id查询所有用户信息 联系方式 部门信息  -->
	<repository>
	    <name>GetUserInfoByInstService</name>
	    <action>com.yun9.sys.inst.support.service.GetUserInfoByInstService</action>
		<output>
			<classname>com.yun9.mobile.framework.model.UserBean</classname>
			<type>list</type>
		</output>
		<type>yun9</type>
	</repository>
	
	<!--根据組織id查询所有用户信息  联系方式 部门信息  -->
	<repository>
	    <name>GetUserInfoByOrgService</name>
	    <action>com.yun9.sys.inst.support.service.GetUserInfoByOrgService</action>
		<output>
			<classname>com.yun9.mobile.framework.model.UserBean</classname>
			<type>list</type>
		</output>
		<type>yun9</type>
	</repository>
	
	<!-- 修改密码 -->
	<repository>
	    <name>SysUserPasswdUpdatePasswdService</name>
	    <action>com.yun9.sys.inst.support.service.SysUserPasswdUpdatePasswdService</action>
		<output>
			<classname>com.yun9.mobile.framework.model.UserPassword</classname>
			<type>object</type>
		</output>
		<type>yun9</type>
	</repository>
	<!--用户设备注册  -->
	<repository>
	    <name>SysUserDeviceRegisterService</name>
	    <action>com.yun9.sys.user.service.SysUserDeviceRegisterService</action>
		<output>
			<classname>com.yun9.mobile.framework.model.DeviceRegisterInfo</classname>
			<type>object</type>
		</output>
		<type>yun9</type>
	</repository>
	
	<!--用户设备注册  -->
	<repository>
	    <name>SysUserUpdateHeaderfileidService</name>
	    <action>com.yun9.sys.inst.support.service.SysUserUpdateHeaderfileidService</action>
		<output>
			<classname>java.util.Map</classname>
			<type>object</type>
		</output>
		<type>yun9</type>
	</repository>
	
</repositorys>